Workbook

Sheet cleaning_top_occupations
A1: occupation | B1: meta_occupation | C1: supercategory | D1: count_occupation | E1: erase | F1: argument | G1: non-living world | H1: living world | I1: animals | J1: non animal living world (plants, microbes, etc.) | K1: human world | L1: category used for cluster analysis?
A2: entomologist | B2: zoologist | D2: 1149 | H2: 1 | I2: 1 | L2: 1
A3: zoologist | B3: zoologist | C3: 1 | D3: 1037 | H3: 1 | I3: 1 | L3: 1
A4: university teacher | B4: university teacher | D4: 3385 | E4: 1
A5: ornithologist | B5: zoologist | D5: 622 | H5: 1 | I5: 1 | L5: 1
A6: explorer | B6: explorer | D6: 2486 | E6: 1
A7: lepidopterist | B7: zoologist | D7: 202 | H7: 1 | I7: 1 | L7: 1
A8: malacologist | B8: zoologist | D8: 187 | H8: 1 | I8: 1 | L8: 1
A9: pedagogue | B9: pedagogue | D9: 1871 | E9: 1
A10: ichthyologist | B10: zoologist | D10: 133 | H10: 1 | I10: 1 | L10: 1
A11: herpetologist | B11: zoologist | D11: 67 | H11: 1 | I11: 1 | L11: 0
A12: carcinologist | B12: zoologist | D12: 60 | H12: 1 | I12: 1 | L12: 1
A13: arachnologist | B13: zoologist | D13: 58 | H13: 1 | I13: 1 | L13: 1
A14: marine biologist | B14: zoologist | D14: 34 | H14: 1 | I14: 1 | L14: 0
A15: coleopterist | B15: zoologist | D15: 14 | H15: 1 | I15: 1 | L15: 1
A16: mammalogist | B16: zoologist | D16: 11 | H16: 1 | L16: 1
A17: zoological collector | B17: zoological collector | D17: 2 | L17: 1
A18: composer | B18: composer | D18: 1038 | E18: 1
A19: weapon historian | B19: weapon historian | D19: 1 | L19: 0
A20: music pedagogue | B20: music pedagogue | D20: 984 | E20: 1
A21: volapükologist | B21: volapükologist | D21: 1 | L21: 1
A22: scientist | B22: scientist | D22: 1095 | E22: 1
A23: virologist | B23: virologist | D23: 3 | L23: 0
A24: ventriloquist | B24: ventriloquist | D24: 1 | L24: 1
A25: toxicologist | B25: toxicologist | D25: 7 | L25: 1
A26: topologist | B26: topologist | D26: 3 | L26: 0
A27: poet | B27: poet | D27: 593 | E27: 1
A28: tibetologist | B28: tibetologist | D28: 1 | L28: 1
A29: translator | B29: translator | D29: 517 | E29: 1
A30: theoretical physicist | B30: theoretical physicist | D30: 8 | L30: 1
A31: painter | B31: painter | D31: 446 | E31: 1
A32: professor | B32: professor | D32: 427 | E32: 1
A33: theologian | B33: theologian | D33: 456 | F33: 1 | L33: 0
A34: theatrologist | B34: theatrologist | D34: 2 | L34: 1
A35: textile scientist | B35: textile scientist | D35: 5 | L35: 0
A36: architect | B36: architect | D36: 371 | E36: 1
A37: teuthologist | B37: teuthologist | D37: 1 | L37: 1
A38: taxonomist | B38: taxonomist | D38: 17 | H38: 1 | L38: 0
A39: spongiologist | B39: spongiologist | D39: 2 | L39: 0
A40: soil scientist | B40: soil scientist | D40: 3 | L40: 0
A41: sociologist | B41: sociologist | D41: 131 | K41: 1 | L41: 0
A42: statistician | B42: statistician | D42: 274 | E42: 1
A43: social scientist | B43: social scientist | D43: 1 | L43: 1
A44: pianist | B44: pianist | D44: 276 | E44: 1
A45: land surveyor | B45: land surveyor | D45: 242 | E45: 1
A46: conductor | B46: conductor | D46: 252 | E46: 1
A47: social politician | B47: social politician | D47: 2 | L47: 0
A48: slavicist | B48: slavicist | D48: 8 | L48: 0
A49: selenographer | B49: selenographer | D49: 2 | L49: 0
A50: photographer | B50: photographer | D50: 182 | E50: 1
A51: metallurgist | B51: metallurgist | D51: 183 | E51: 1
A52: horticulturist | B52: horticulturist | D52: 181 | E52: 1
A53: Scandinavian studies scholar | B53: Scandinavian studies scholar | D53: 1 | L53: 0
A54: Sanskrit scholar | B54: Sanskrit scholar | D54: 1 | L54: 0
A55: organist | B55: organist | D55: 171 | E55: 1
A56: runologist | B56: runologist | D56: 6 | L56: 1
A57: religious studies scholar | B57: religious studies scholar | D57: 1 | L57: 0
A58: drawer | B58: drawer | D58: 138 | E58: 1
A59: ironmaster | B59: ironmaster | D59: 124 | E59: 1
A60: scientific illustrator | B60: scientific illustrator | D60: 126 | E60: 1
A61: racial theorist | B61: racial theorist | D61: 5 | L61: 0
A62: protistologist | B62: protistologist | D62: 1 | L62: 0
A63: musician | B63: musician | D63: 140 | E63: 1
A64: professor of physics | B64: professor of physics | D64: 1 | L64: 1
A65: political theorist | B65: political theorist | D65: 7 | L65: 1
A66: political scientist | B66: political scientist | D66: 60 | K66: 1 | L66: 0
A67: neurologist | B67: neurologist | D67: 120 | E67: 1
A68: singer | B68: singer | D68: 126 | E68: 1
A69: illustrator | B69: illustrator | D69: 115 | E69: 1
A70: plant physiologist | B70: plant physiologist | D70: 2 | L70: 0
A71: opera singer | B71: opera singer | D71: 122 | E71: 1
A72: plant cell biologist | B72: plant cell biologist | D72: 1 | L72: 0
A73: physicist | B73: physicist | D73: 1381 | G73: 1 | L73: 0
A74: engraver | B74: engraver | D74: 98 | E74: 1
A75: artist | B75: artist | D75: 96 | E75: 1
A76: urban planner | B76: urban planner | D76: 101 | E76: 1
A77: physical chemist | B77: physical chemist | D77: 2 | L77: 0
A78: philosophy historian | B78: philosophy historian | D78: 1 | L78: 0
A79: curator | B79: curator | D79: 88 | E79: 1
A80: non-fiction writer | B80: non-fiction writer | D80: 90 | E80: 1
A81: editor | B81: editor | D81: 94 | E81: 1
A82: philosopher of science | B82: philosopher of science | D82: 1 | L82: 0
A83: violinist | B83: violinist | D83: 97 | E83: 1
A84: botanical illustrator | B84: botanical illustrator | D84: 81 | E84: 1
A85: philosopher of language | B85: philosopher of language | D85: 1 | L85: 0
A86: collector of fairy tales | B86: collector of fairy tales | D86: 81 | E86: 1
A87: philosopher | B87: philosopher | D87: 830 | F87: 1 | L87: 0
A88: playwright | B88: playwright | D88: 87 | E88: 1
A89: opinion journalist | B89: opinion journalist | D89: 107 | E89: 1
A90: pharmacologist | B90: pharmacologist | D90: 132 | G90: 1 | L90: 0
A91: petrologist | B91: petrologist | D91: 2 | L91: 0
A92: academic | B92: academic | D92: 71 | E92: 1
A93: conquistador | B93: conquistador | D93: 113 | E93: 1
A94: petroleum geologist | B94: petroleum geologist | D94: 1 | L94: 1
A95: encyclopédistes | B95: encyclopédistes | D95: 55 | E95: 1
A96: children's writer | B96: children's writer | D96: 61 | E96: 1
A97: world traveler | B97: world traveler | D97: 69 | E97: 1
A98: petrographer | B98: petrographer | D98: 2 | L98: 0
A99: printmaker | B99: printmaker | D99: 52 | E99: 1
A100: pedologist | B100: pedologist | D100: 1 | L100: 0
...

Sheet co_occurence_occupation
A1: source | B1: target | C1: weight | D1: remove_occupation | E1: action
A2: anatomist | B2: biologist | C2: 73 | D2: biologist
A3: anatomist | B3: botanist | C3: 86
A4: anatomist | B4: ecologist | C4: 1
A5: anatomist | B5: naturalist | C5: 33
A6: anatomist | B6: zoologist | C6: 127
A7: biologist | B7: anatomist | C7: 73 | D7: biologist
A8: biologist | B8: botanist | C8: 155 | D8: biologist
A9: biologist | B9: ecologist | C9: 2 | D9: biologist
A10: biologist | B10: naturalist | C10: 82 | D10: biologist | E10: impute missing data: proportion of anatomist / botanist / zoologist
A11: biologist | B11: zoologist | C11: 200 | D11: biologist
A12: botanist | B12: anatomist | C12: 86
A13: botanist | B13: biologist | C13: 155
A14: botanist | B14: ecologist | C14: 9
A15: botanist | B15: naturalist | C15: 407
A16: botanist | B16: zoologist | C16: 733
A17: ecologist | B17: anatomist | C17: 1
A18: ecologist | B18: biologist | C18: 2
A19: ecologist | B19: botanist | C19: 9
A20: ecologist | B20: naturalist | C20: 3
A21: ecologist | B21: zoologist | C21: 5
A22: naturalist | B22: anatomist | C22: 33 | D22: naturalist
A23: naturalist | B23: biologist | C23: 82 | D23: biologist | E23: impute missing data: proportion of anatomist / botanist / zoologist
A24: naturalist | B24: botanist | C24: 407 | D24: naturalist
A25: naturalist | B25: ecologist | C25: 3 | D25: naturalist
A26: naturalist | B26: zoologist | C26: 513 | D26: naturalist
A27: zoologist | B27: anatomist | C27: 127
A28: zoologist | B28: biologist | C28: 200
A29: zoologist | B29: botanist | C29: 733
A30: zoologist | B30: ecologist | C30: 5
A31: zoologist | B31: naturalist | C31: 513

Sheet sbert_occupation
A1: occupation | B1: score | C1: order | D1: count_occupation | E1: meta_occupation
A2: organic chemist | B2: 9.9706545 | C2: 0 | D2: =VLOOKUP(A2,cleaning_top_occupations!A:D,2,False) -> organic chemist
A3: physical chemist | B3: 9.947152 | C3: 1 | D3: =VLOOKUP(A3,cleaning_top_occupations!A:D,2,False) -> physical chemist
A4: food chemist | B4: 9.861608 | C4: 2 | D4: =VLOOKUP(A4,cleaning_top_occupations!A:D,2,False) -> food chemist
A5: chemist | B5: 9.837849 | C5: 3 | D5: =VLOOKUP(A5,cleaning_top_occupations!A:D,2,False) -> chemist
A6: inorganic chemist | B6: 9.8108 | C6: 4 | D6: =VLOOKUP(A6,cleaning_top_occupations!A:D,2,False) -> inorganic chemist
A7: chemical technologist | B7: 9.740687 | C7: 5 | D7: =VLOOKUP(A7,cleaning_top_occupations!A:D,2,False) -> chemical technologist
A8: agricultural chemist | B8: 9.724198 | C8: 6 | D8: =VLOOKUP(A8,cleaning_top_occupations!A:D,2,False) -> agricultural chemist
A9: chemical engineer | B9: 9.698211 | C9: 7 | D9: =VLOOKUP(A9,cleaning_top_occupations!A:D,2,False) -> chemical engineer
A10: agricultural engineer | B10: 9.549633 | C10: 8 | D10: =VLOOKUP(A10,cleaning_top_occupations!A:D,2,False) -> agricultural engineer
A11: agricultural economist | B11: 9.5345 | C11: 9 | D11: =VLOOKUP(A11,cleaning_top_occupations!A:D,2,False) -> agricultural economist
A12: agronomist | B12: 9.41823 | C12: 10 | D12: =VLOOKUP(A12,cleaning_top_occupations!A:D,2,False) -> botanist
A13: agrostologist | B13: 9.394546 | C13: 11 | D13: =VLOOKUP(A13,cleaning_top_occupations!A:D,2,False) -> agrostologist
... A297: Germanist | B297: 3.9880264 | C297: 295 | D297: =VLOOKUP(A297,cleaning_top_occupations!A:D,2,False) -> Germanist

Sheet pairwise_comparison_top_occupat
A1: pair | B1: percent_similarity | C1: len | D1: pair_1 | E1: pair_2
A2: ('Germany', 'Italy') | B2: 80 | C2: [5, 5] | D2: ['botanist', 'mathematician', 'chemist', 'astronomer', 'physicist'] | E2: ['mathematician', 'botanist', 'archaeologist', 'astronomer', 'physicist']
A3: ('Japan', 'United Kingdom') | B3: 80 | C3: [5, 5] | D3: ['mathematician', 'astronomer', 'political scientist', 'botanist', 'explorer'] | E3: ['botanist', 'explorer', 'mathematician', 'naturalist', 'astronomer']
A4: ('Arabic world', 'Chinese world') | B4: 60 | C4: [5, 5] | D4: ['mathematician', 'astronomer', 'historian', 'linguist', 'geographer'] | E4: ['mathematician', 'astronomer', 'explorer', 'historian', 'philosopher']
A5: ('Japan', 'France') | B5: 60 | C5: [5, 5] | D5: ['mathematician', 'astronomer', 'political scientist', 'botanist', 'explorer'] | E5: ['botanist', 'explorer', 'mathematician', 'archaeologist', 'chemist']
A6: ('Germany', 'United Kingdom') | B6: 60 | C6: [5, 5] | D6: ['botanist', 'mathematician', 'chemist', 'astronomer', 'physicist'] | E6: ['botanist', 'explorer', 'mathematician', 'naturalist', 'astronomer']
A7: ('France', 'Italy') | B7: 60 | C7: [5, 5] | D7: ['botanist', 'explorer', 'mathematician', 'archaeologist', 'chemist'] | E7: ['mathematician', 'botanist', 'archaeologist', 'astronomer', 'physicist']
A8: ('France', 'United Kingdom') | B8: 60 | C8: [5, 5] | D8: ['botanist', 'explorer', 'mathematician', 'archaeologist', 'chemist'] | E8: ['botanist', 'explorer', 'mathematician', 'naturalist', 'astronomer']
A9: ('France', 'Germany') | B9: 60 | C9: [5, 5] | D9: ['botanist', 'explorer', 'mathematician', 'archaeologist', 'chemist'] | E9: ['botanist', 'mathematician', 'chemist', 'astronomer', 'physicist']
A10: ('Japan', 'Italy') | B10: 60 | C10: [5, 5] | D10: ['mathematician', 'astronomer', 'political scientist', 'botanist', 'explorer'] | E10: ['mathematician', 'botanist', 'archaeologist', 'astronomer', 'physicist']
A11: ('Japan', 'Germany') | B11: 60 | C11: [5, 5] | D11: ['mathematician', 'astronomer', 'political scientist', 'botanist', 'explorer'] | E11: ['botanist', 'mathematician', 'chemist', 'astronomer', 'physicist']
A12: ('United Kingdom', 'Italy') | B12: 60 | C12: [5, 5] | D12: ['botanist', 'explorer', 'mathematician', 'naturalist', 'astronomer'] | E12: ['mathematician', 'botanist', 'archaeologist', 'astronomer', 'physicist']
A13: ('Chinese world', 'United Kingdom') | B13: 60 | C13: [5, 5] | D13: ['mathematician', 'astronomer', 'explorer', 'historian', 'philosopher'] | E13: ['botanist', 'explorer', 'mathematician', 'naturalist', 'astronomer']
... A22: ('Arabic world', 'France') | B22: 20 | C22: [5, 5] | D22: ['mathematician', 'astronomer', 'historian', 'linguist', 'geographer'] | E22: ['botanist', 'explorer', 'mathematician', 'archaeologist', 'chemist']

Sheet newton_wikipage_links
A1: name | B1: links | C1: wikidata_id | D1: wikidata_link
A2: Isaac Newton | B2: s Gravesande | C2: Q1384858 | D2: https://www.wikidata.org/wiki/Q1384858
A3: Isaac Newton | B3: 1705 English general election | C3: Q5378579 | D3: https://www.wikidata.org/wiki/Q5378579
A4: Isaac Newton | B4: 1 John 5:7 | C4: Q1115006 | D4: https://www.wikidata.org/wiki/Q1115006
A5: Isaac Newton | B5: 2dF Galaxy Redshift Survey | C5: Q2815842 | D5: https://www.wikidata.org/wiki/Q2815842
A6: Isaac Newton | B6: ASIN (identifier) | C6: Q1753278 | D6: https://www.wikidata.org/wiki/Q1753278
A7: Isaac Newton | B7: A History of the Theories of Aether and Electricity | C7: Q99703332 | D7: https://www.wikidata.org/wiki/Q99703332
A8: Isaac Newton | B8: A priori and a posteriori | C8: Q178161 | D8: https://www.wikidata.org/wiki/Q178161
A9: Isaac Newton | B9: Aaron Guerdon
A10: Isaac Newton | B10: Aaron Klug | C10: Q190626 | D10: https://www.wikidata.org/wiki/Q190626
A11: Isaac Newton | B11: Abraham de Moivre | C11: Q200397 | D11: https://www.wikidata.org/wiki/Q200397
A12: Isaac Newton | B12: Abraham de la Pryme | C12: Q4669280 | D12: https://www.wikidata.org/wiki/Q4669280
A13: Isaac Newton | B13: Absolute space and time | C13: Q19314 | D13: https://www.wikidata.org/wiki/Q19314
A14: Isaac Newton | B14: Abstract and concrete | C14: Q18205125 | D14: https://www.wikidata.org/wiki/Q18205125
A15: Isaac Newton | B15: Abstract object theory | C15: Q16000046 | D15: https://www.wikidata.org/wiki/Q16000046
A16: Isaac Newton | B16: Abu'l Hasan ibn Arfa Ra'a | C16: Q16148550 | D16: https://www.wikidata.org/wiki/Q16148550
A17: Isaac Newton | B17: Action at a distance (physics) | C17: Q1407429 | D17: https://www.wikidata.org/wiki/Q1407429
A18: Isaac Newton | B18: Action theory (philosophy) | C18: Q175661 | D18: https://www.wikidata.org/wiki/Q175661
A19: Isaac Newton | B19: Adam Ferguson | C19: Q183094 | D19: https://www.wikidata.org/wiki/Q183094
A20: Isaac Newton | B20: Adam Smith | C20: Q9381 | D20: https://www.wikidata.org/wiki/Q9381
A21: Isaac Newton | B21: Adam Weishaupt | C21: Q159481 | D21: https://www.wikidata.org/wiki/Q159481
... A591: Isaac Newton | B591: James Harrington (author) | C591: Q969183 | D591: https://www.wikidata.org/wiki/Q969183
A592: Isaac Newton | B592: James Hoare (gold merchant)
A593: Isaac Newton | B593: James Hutton | C593: Q192927 | D593: https://www.wikidata.org/wiki/Q192927
A594: Isaac Newton | B594: James Jurin | C594: Q1959556 | D594: https://www.wikidata.org/wiki/Q1959556
A595: Isaac Newton | B595: James Lighthill | C595: Q944275 | D595: https://www.wikidata.org/wiki/Q944275
A596: Isaac Newton | B596: James Madison | C596: Q11813 | D596: https://www.wikidata.org/wiki/Q11813
A597: Isaac Newton | B597: James Mill | C597: Q271666 | D597: https://www.wikidata.org/wiki/Q271666
A598: Isaac Newton | B598: James Prescott Joule | C598: Q8962 | D598: https://www.wikidata.org/wiki/Q8962
A599: Isaac Newton | B599: James Stirling (mathematician) | C599: Q437734 | D599: https://www.wikidata.org/wiki/Q437734
A600: Isaac Newton | B600: James Watt | C600: Q9041 | D600: https://www.wikidata.org/wiki/Q9041
A601: Isaac Newton | B601: James West (antiquary) | C601: Q6145348 | D601: https://www.wikidata.org/wiki/Q6145348
A602: Isaac Newton | B602: Jan Baptist van Helmont | C602: Q294169 | D602: https://www.wikidata.org/wiki/Q294169
A603: Isaac Newton | B603: Jan Swammerdam | C603: Q336794 | D603: https://www.wikidata.org/wiki/Q336794
A604: Isaac Newton | B604: Jean-Jacques Burlamaqui | C604: Q966930 | D604: https://www.wikidata.org/wiki/Q966930
... A1016: Isaac Newton | B1016: Ramon Llull | C1016: Q193660 | D1016: https://www.wikidata.org/wiki/Q193660
A1017: Isaac Newton | B1017: Randal Cranfield
A1018: Isaac Newton | B1018: Rankine scale | C1018: Q207488 | D1018: https://www.wikidata.org/wiki/Q207488
A1019: Isaac Newton | B1019: Rashid Sunyaev | C1019: Q836911 | D1019: https://www.wikidata.org/wiki/Q836911
A1020: Isaac Newton | B1020: Rationalism | C1020: Q483024 | D1020: https://www.wikidata.org/wiki/Q483024
A1021: Isaac Newton | B1021: Rationalist | C1021: Q483024 | D1021: https://www.wikidata.org/wiki/Q483024
A1022: Isaac Newton | B1022: Rationality | C1022: Q938185 | D1022: https://www.wikidata.org/wiki/Q938185
A1023: Isaac Newton | B1023: Rayl | C1023: Q359151 | D1023: https://www.wikidata.org/wiki/Q359151
A1024: Isaac Newton | B1024: Reality | C1024: Q9510 | D1024: https://www.wikidata.org/wiki/Q9510
A1025: Isaac Newton | B1025: Reason | C1025: Q178354 | D1025: https://www.wikidata.org/wiki/Q178354
A1026: Isaac Newton | B1026: Rebis | C1026: Q3931255 | D1026: https://www.wikidata.org/wiki/Q3931255
A1027: Isaac Newton | B1027: Received view of theories | C1027: Q7302321 | D1027: https://www.wikidata.org/wiki/Q7302321
A1028: Isaac Newton | B1028: Redshift | C1028: Q76250 | D1028: https://www.wikidata.org/wiki/Q76250
A1029: Isaac Newton | B1029: Reductionism | C1029: Q206829 | D1029: https://www.wikidata.org/wiki/Q206829
... A1347: Isaac Newton | B1347: Wikipedia:Wikimedia sister projects | C1347: Q10823887 | D1347: https://www.wikidata.org/wiki/Q10823887
A1348: Isaac Newton | B1348: File:Isaac Newton.ogg
A1349: Isaac Newton | B1349: Template:Age of Enlightenment | C1349: Q10962287 | D1349: https://www.wikidata.org/wiki/Q10962287
A1350: Isaac Newton | B1350: Template:Alchemy | C1350: Q6675323 | D1350: https://www.wikidata.org/wiki/Q6675323
A1351: Isaac Newton | B1351: Template:Cite web | C1351: Q5637226 | D1351: https://www.wikidata.org/wiki/Q5637226
A1352: Isaac Newton | B1352: Template:Isaac Newton | C1352: Q22734651 | D1352: https://www.wikidata.org/wiki/Q22734651
A1353: Isaac Newton | B1353: Template:Lucasian Professors of Mathematics | C1353: Q14407392 | D1353: https://www.wikidata.org/wiki/Q14407392
A1354: Isaac Newton | B1354: Template:Masters of the Mint
A1355: Isaac Newton | B1355: Template:Metaphysics | C1355: Q8084282 | D1355: https://www.wikidata.org/wiki/Q8084282
A1356: Isaac Newton | B1356: Template:Philosophy of science | C1356: Q8084428 | D1356: https://www.wikidata.org/wiki/Q8084428
A1357: Isaac Newton | B1357: Template:Physical cosmology | C1357: Q8078638 | D1357: https://www.wikidata.org/wiki/Q8078638
A1358: Isaac Newton | B1358: Template:Romanticism | C1358: Q8085027 | D1358: https://www.wikidata.org/wiki/Q8085027
A1359: Isaac Newton | B1359: Template:Royal Society presidents | C1359: Q14456067 | D1359: https://www.wikidata.org/wiki/Q14456067
A1360: Isaac Newton | B1360: Template:S-par/en | C1360: Q14446550 | D1360: https://www.wikidata.org/wiki/Q14446550
A1361: Isaac Newton | B1361: Template:Scientists whose names are used as units | C1361: Q11023919 | D1361: https://www.wikidata.org/wiki/Q11023919
A1362: Isaac Newton | B1362: Template talk:Age of Enlightenment
A1363: Isaac Newton | B1363: Template talk:Alchemy
A1364: Isaac Newton | B1364: Template talk:Isaac Newton
A1365: Isaac Newton | B1365: Template talk:Lucasian Professors of Mathematics
A1366: Isaac Newton | B1366: Template talk:Masters of the Mint
A1367: Isaac Newton | B1367: Template talk:Metaphysics
A1368: Isaac Newton | B1368: Template talk:Philosophy of science
A1369: Isaac Newton | B1369: Template talk:Physical cosmology
A1370: Isaac Newton | B1370: Template talk:Royal Society presidents
A1371: Isaac Newton | B1371: Template talk:Scientists whose names are used as units
A1372: Isaac Newton | B1372: Help:Authority control | C1372: Q8614281 | D1372: https://www.wikidata.org/wiki/Q8614281
A1373: Isaac Newton | B1373: Category:Age of Enlightenment | C1373: Q6489876 | D1373: https://www.wikidata.org/wiki/Q6489876
A1374: Isaac Newton | B1374: Category:Alchemical documents | C1374: Q8234214 | D1374: https://www.wikidata.org/wiki/Q8234214
A1375: Isaac Newton | B1375: Category:Alchemical processes | C1375: Q8234220 | D1375: https://www.wikidata.org/wiki/Q8234220
A1376: Isaac Newton | B1376: Category:Alchemy | C1376: Q7216265 | D1376: https://www.wikidata.org/wiki/Q7216265
A1377: Isaac Newton | B1377: Category:Articles prone to spam from December 2018
A1378: Isaac Newton | B1378: Category:Articles with BIBSYS identifiers | C1378: Q8922188 | D1378: https://www.wikidata.org/wiki/Q8922188
A1379: Isaac Newton | B1379: Category:Articles with BNC identifiers | C1379: Q65974970 | D1379: https://www.wikidata.org/wiki/Q65974970
A1380: Isaac Newton | B1380: Category:Articles with BNE identifiers | C1380: Q18174793 | D1380: https://www.wikidata.org/wiki/Q18174793
A1381: Isaac Newton | B1381: Category:Articles with BNF identifiers | C1381: Q8922190 | D1381: https://www.wikidata.org/wiki/Q8922190
A1382: Isaac Newton | B1382: Category:Articles with BNFdata identifiers | C1382: Q117197805 | D1382: https://www.wikidata.org/wiki/Q117197805
A1383: Isaac Newton | B1383: Category:Articles with BNMM identifiers | C1383: Q111608207 | D1383: https://www.wikidata.org/wiki/Q111608207
A1384: Isaac Newton | B1384: Category:Articles with CANTICN identifiers | C1384: Q111193492 | D1384: https://www.wikidata.org/wiki/Q111193492
A1385: Isaac Newton | B1385: Category:Articles with CINII identifiers | C1385: Q55404415 | D1385: https://www.wikidata.org/wiki/Q55404415
A1386: Isaac Newton | B1386: Category:Articles with DTBIO identifiers | C1386: Q111044368 | D1386: https://www.wikidata.org/wiki/Q111044368
A1387: Isaac Newton | B1387: Category:Articles with FAST identifiers | C1387: Q61034957 | D1387: https://www.wikidata.org/wiki/Q61034957
A1388: Isaac Newton | B1388: Category:Articles with GND identifiers | C1388: Q8922195 | D1388: https://www.wikidata.org/wiki/Q8922195
A1389: Isaac Newton | B1389: Category:Articles with Google Scholar identifiers | C1389: Q110985685 | D1389: https://www.wikidata.org/wiki/Q110985685
... A1407: Isaac Newton | B1407: Category:Articles with PLWABN identifiers | C1407: Q104668293 | D1407: https://www.wikidata.org/wiki/Q104668293
A1408: Isaac Newton | B1408: Category:Articles with PortugalA identifiers
A1409: Isaac Newton | B1409: Category:Articles with SNAC-ID identifiers | C1409: Q37412445 | D1409: https://www.wikidata.org/wiki/Q37412445
A1410: Isaac Newton | B1410: Category:Articles with SUDOC identifiers | C1410: Q18174754 | D1410: https://www.wikidata.org/wiki/Q18174754
A1411: Isaac Newton | B1411: Category:Articles with Trove identifiers | C1411: Q66847346 | D1411: https://www.wikidata.org/wiki/Q66847346
A1412: Isaac Newton | B1412: Category:Articles with ULAN identifiers | C1412: Q8922201 | D1412: https://www.wikidata.org/wiki/Q8922201
A1413: Isaac Newton | B1413: Category:Articles with VIAF identifiers | C1413: Q8922203 | D1413: https://www.wikidata.org/wiki/Q8922203
A1414: Isaac Newton | B1414: Category:Articles with VcBA identifiers | C1414: Q97411455 | D1414: https://www.wikidata.org/wiki/Q97411455
...

Sheet Sheet9
A1: pair | B1: percent_similarity | C1: len | D1: pair_1 | E1: pair_2
A2: ('France', 'Italy') | B2: 90 | C2: [10, 10] | D2: ['botanist', 'explorer', 'mathematician', 'archaeologist', 'chemist', 'physicist', 'naturalist', 'historian', 'astronomer', 'economist'] | E2: ['mathematician', 'botanist', 'archaeologist', 'astronomer', 'physicist', 'economist', 'philosopher', 'explorer', 'historian', 'naturalist']
A3: ('France', 'Germany') | B3: 80 | C3: [10, 10] | D3: ['botanist', 'explorer', 'mathematician', 'archaeologist', 'chemist', 'physicist', 'naturalist', 'historian', 'astronomer', 'economist'] | E3: ['botanist', 'mathematician', 'chemist', 'astronomer', 'physicist', 'entomologist', 'naturalist', 'zoologist', 'archaeologist', 'economist']
A4: ('Germany', 'Italy') | B4: 70 | C4: [10, 10] | D4: ['botanist', 'mathematician', 'chemist', 'astronomer', 'physicist', 'entomologist', 'naturalist', 'zoologist', 'archaeologist', 'economist'] | E4: ['mathematician', 'botanist', 'archaeologist', 'astronomer', 'physicist', 'economist', 'philosopher', 'explorer', 'historian', 'naturalist']
A5: ('Germany', 'United Kingdom') | B5: 70 | C5: [10, 10] | D5: ['botanist', 'mathematician', 'chemist', 'astronomer', 'physicist', 'entomologist', 'naturalist', 'zoologist', 'archaeologist', 'economist'] | E5: ['botanist', 'explorer', 'mathematician', 'naturalist', 'astronomer', 'chemist', 'geologist', 'zoologist', 'physicist', 'ornithologist']
A6: ('France', 'United Kingdom') | B6: 70 | C6: [10, 10] | D6: ['botanist', 'explorer', 'mathematician', 'archaeologist', 'chemist', 'physicist', 'naturalist', 'historian', 'astronomer', 'economist'] | E6: ['botanist', 'explorer', 'mathematician', 'naturalist', 'astronomer', 'chemist', 'geologist', 'zoologist', 'physicist', 'ornithologist']
A7: ('Chinese world', 'Japan') | B7: 70 | C7: [10, 10] | D7: ['mathematician', 'astronomer', 'explorer', 'historian', 'philosopher', 'geographer', 'calligrapher', 'cartographer', 'botanist', 'anthropologist'] | E7: ['mathematician', 'astronomer', 'political scientist', 'botanist', 'explorer', 'philosopher', 'agronomist', 'economist', 'geographer', 'cartographer']
A8: ('Arabic world', 'Chinese world') | B8: 60 | C8: [10, 10] | D8: ['mathematician', 'astronomer', 'historian', 'linguist', 'geographer', 'chemist', 'explorer', 'philologist', 'philosopher', 'archaeologist'] | E8: ['mathematician', 'astronomer', 'explorer', 'historian', 'philosopher', 'geographer', 'calligrapher', 'cartographer', 'botanist', 'anthropologist']
A9: ('Japan', 'Italy') | B9: 60 | C9: [10, 10] | D9: ['mathematician', 'astronomer', 'political scientist', 'botanist', 'explorer', 'philosopher', 'agronomist', 'economist', 'geographer', 'cartographer'] | E9: ['mathematician', 'botanist', 'archaeologist', 'astronomer', 'physicist', 'economist', 'philosopher', 'explorer', 'historian', 'naturalist']
A10: ('Chinese world', 'Italy') | B10: 60 | C10: [10, 10] | D10: ['mathematician', 'astronomer', 'explorer', 'historian', 'philosopher', 'geographer', 'calligrapher', 'cartographer', 'botanist', 'anthropologist'] | E10: ['mathematician', 'botanist', 'archaeologist', 'astronomer', 'physicist', 'economist', 'philosopher', 'explorer', 'historian', 'naturalist']
A11: ('Arabic world', 'Italy') | B11: 60 | C11: [10, 10] | D11: ['mathematician', 'astronomer', 'historian', 'linguist', 'geographer', 'chemist', 'explorer', 'philologist', 'philosopher', 'archaeologist'] | E11: ['mathematician', 'botanist', 'archaeologist', 'astronomer', 'physicist', 'economist', 'philosopher', 'explorer', 'historian', 'naturalist']
A12: ('Arabic world', 'France') | B12: 60 | C12: [10, 10] | D12: ['mathematician', 'astronomer', 'historian', 'linguist', 'geographer', 'chemist', 'explorer', 'philologist', 'philosopher', 'archaeologist'] | E12: ['botanist', 'explorer', 'mathematician', 'archaeologist', 'chemist', 'physicist', 'naturalist', 'historian', 'astronomer', 'economist']
A13: ('United Kingdom', 'Italy') | B13: 60 | C13: [10, 10] | D13: ['botanist', 'explorer', 'mathematician', 'naturalist', 'astronomer', 'chemist', 'geologist', 'zoologist', 'physicist', 'ornithologist'] | E13: ['mathematician', 'botanist', 'archaeologist', 'astronomer', 'physicist', 'economist', 'philosopher', 'explorer', 'historian', 'naturalist']
... A22: ('Chinese world', 'Germany') | B22: 30 | C22: [10, 10] | D22: ['mathematician', 'astronomer', 'explorer', 'historian', 'philosopher', 'geographer', 'calligrapher', 'cartographer', 'botanist', 'anthropologist'] | E22: ['botanist', 'mathematician', 'chemist', 'astronomer', 'physicist', 'entomologist', 'naturalist', 'zoologist', 'archaeologist', 'economist']
